AUTHORS
ChangeLog
LICENSE
README.md
setup.cfg
setup.py
csh_uuid/__init__.py
csh_uuid.egg-info/PKG-INFO
csh_uuid.egg-info/SOURCES.txt
csh_uuid.egg-info/dependency_links.txt
csh_uuid.egg-info/not-zip-safe
csh_uuid.egg-info/pbr.json
csh_uuid.egg-info/requires.txt
csh_uuid.egg-info/top_level.txt